syrabrox/__init__.py
syrabrox/main.py
syrabrox-4.0.0.dist-info/METADATA
syrabrox-4.0.0.dist-info/WHEEL
syrabrox-4.0.0.dist-info/top_level.txt
syrabrox-4.0.0.dist-info/RECORD
