Metadata-Version: 2.1
Name: syrabrox
Version: 4.0.0
